django_security_tools/__init__.py
django_security_tools/admin.py
django_security_tools/apps.py
django_security_tools/decorators.py
django_security_tools/models.py
django_security_tools/views.py
django_security_tools/migrations/0001_initial.py
django_security_tools/migrations/__init__.py
django_security_tools/templates/django-security-tools/index.html
django_security_tools/tests/__init__.py
django_security_tools-0.0.1.dist-info/METADATA
django_security_tools-0.0.1.dist-info/WHEEL
django_security_tools-0.0.1.dist-info/licenses/LICENSE
django_security_tools-0.0.1.dist-info/RECORD
