Metadata-Version: 2.4
Name: django-security-tools
Version: 0.0.1
Summary: A set of security tools for Django.
Project-URL: Homepage, https://github.com/dreamxinxcode/django-security-tools
Project-URL: Issues, https://github.com/dreamxinxcode/django-security-tools/issues
Author-email: Brandon Lecky <brandon@dreamincode.dev>
License-Expression: MIT
License-File: LICENSE
Classifier: Operating System :: OS Independent
Classifier: Programming Language :: Python :: 3
Requires-Python: >=3.8
